{
   "items": [
      {
         "id": "sadf",
         "name": "sfad",
         "pluginDescriptorRef": {
            "id": "org.sourceid.saml20.domain.SimpleUsernamePasswordCredentialValidator",
            "location": "https://debian-pingfed:9999/pf-admin-api/v1/passwordCredentialValidators/descriptors/org.sourceid.saml20.domain.SimpleUsernamePasswordCredentialValidator"
         },
         "configuration": {
            "tables": [
               {
                  "name": "Users",
                  "rows": [
                     {
                        "fields": [
                           {
                              "name": "Username",
                              "value": "jack"
                           },
                           {
                              "name": "Password",
                              "encryptedValue": "OBF:JWE:eyJhbGciOiJkaXIiLCJlbmMiOiJBMTI4Q0JDLUhTMjU2Iiwia2lkIjoiVEZGZmNIUndlRCIsInZlcnNpb24iOiIxMS4yLjUuMCJ9..K7Z1C5TB17crQk7dyyqy8w.jCeofwRlL44yuBFQMUn5AxqMUYLuJoJsg9IhXLxVSam20ZtfeDzR2x4Rbdca9b3Xot0xo07yUEZ_7yD8QH41tA.qADH3NFk056Vza9CORS8tA"
                           },
                           {
                              "name": "Confirm Password",
                              "encryptedValue": "OBF:JWE:eyJhbGciOiJkaXIiLCJlbmMiOiJBMTI4Q0JDLUhTMjU2Iiwia2lkIjoiVEZGZmNIUndlRCIsInZlcnNpb24iOiIxMS4yLjUuMCJ9..KNDZegTrFYDMvtTr6GpI6g.z1jGvONFrqSIMU9N2-zzB6njDRsBWxt9xDHJV4HFjVsvRTLdS71FuWlVrLuzbFD7py1WMETZopE4_aiixzk2wA.1nPGzDCw7tVP6v3hmM7UEg"
                           },
                           {
                              "name": "Relax Password Requirements",
                              "value": "false"
                           }
                        ],
                        "defaultRow": false
                     }
                  ]
               }
            ],
            "fields": []
         },
         "attributeContract": {
            "coreAttributes": [
               {
                  "name": "username"
               }
            ]
         }
      }
   ]
}